[
  {
    "id": "ChIJazzp3nO7BTsR-p6jRj3weCo",
    "name": "Ujjivan Small Finance Bank - Thiruvananthapuram Main Branch",
    "score": 71.3,
    "rating": 4.9,
    "reviews": 312,
    "price_level": null,
    "address": "No. 73/3, T.K Divakaran Tower, Medical College, Road, P.O, Kumarapuram, Thiruvananthapuram, Kerala 695011, India",
    "image": "images/places/AZLasHoY58IvG04l.jpg",
    "category": "banking",
    "vibes": [
      "Cooperative"
    ],
    "website": "https://www.ujjivansfb.bank.in/static/branches/thiruvananthapurammain-contact-address-ifsc-code.html",
    "phone": "089513 95643",
    "map_url": "https://www.google.com/maps/place/?q=place_id:ChIJazzp3nO7BTsR-p6jRj3weCo",
    "metrics": {
      "sentiment": 100,
      "popularity": 312,
      "convenience": 5
    },
    "locality": "Medical College",
    "types": [
      "bank",
      "finance",
      "point_of_interest",
      "establishment"
    ],
    "location": {
      "lat": 8.5157033,
      "lng": 76.92746939999999
    }
  },
  {
    "id": "ChIJMb91Zcq7BTsR8omhk2SwOkE",
    "name": "Standard Chartered Thiruvananthapuram Branch",
    "score": 64,
    "rating": 4.6,
    "reviews": 179,
    "price_level": null,
    "address": "Ground Floor, Vrindavan Terrace, opposite Vazhuthacaud, Nandavanam, Vazhuthacaud, Thiruvananthapuram, Kerala 695010, India",
    "image": "images/places/AZLasHrtBqCdNXpO.jpg",
    "category": "banking",
    "vibes": [
      "Cooperative"
    ],
    "website": "https://www.sc.com/in/",
    "phone": null,
    "map_url": "https://www.google.com/maps/place/?q=place_id:ChIJMb91Zcq7BTsR8omhk2SwOkE",
    "metrics": {
      "sentiment": 94,
      "popularity": 179,
      "convenience": 5
    },
    "locality": "Vazhuthacaud",
    "types": [
      "bank",
      "finance",
      "point_of_interest",
      "establishment"
    ],
    "location": {
      "lat": 8.5051583,
      "lng": 76.9605929
    }
  },
  {
    "id": "ChIJj4Scn7e7BTsRArwuNDp9vcw",
    "name": "Reserve Bank of India Thiruvananthapuram Branch Office",
    "score": 62.8,
    "rating": 4.6,
    "reviews": 147,
    "price_level": null,
    "address": "No.6507, Bakery Jct Rd, Nandavanam, Palayam, Thiruvananthapuram, Kerala 695033, India",
    "image": "images/places/AZLasHpWvgwukfoj.jpg",
    "category": "banking",
    "vibes": [],
    "website": "https://rbi.org.in/regionalbranch/trivandram/trivandram.aspx",
    "phone": "0471 232 9676",
    "map_url": "https://www.google.com/maps/place/?q=place_id:ChIJj4Scn7e7BTsRArwuNDp9vcw",
    "metrics": {
      "sentiment": 93,
      "popularity": 147,
      "convenience": 5
    },
    "locality": "Palayam",
    "types": [
      "bank",
      "finance",
      "point_of_interest",
      "establishment"
    ],
    "location": {
      "lat": 8.501646200000001,
      "lng": 76.9538512
    }
  },
  {
    "id": "ChIJa6AE7L67BTsRPTd2M5CTlfU",
    "name": "SBI ATM",
    "score": 62.6,
    "rating": 5,
    "reviews": 2,
    "price_level": null,
    "address": "School Jn, opp. St. Thomas Sschool, Jai Vihar, Kunnukuzhy, Thiruvananthapuram, Kerala 695035, India",
    "image": "images/places/AZLasHqqd5CjzZ-a.jpg",
    "category": "banking",
    "vibes": [
      "Public Sector"
    ],
    "website": "https://bank.sbi/",
    "phone": "1800 1234",
    "map_url": "https://www.google.com/maps/place/?q=place_id:ChIJa6AE7L67BTsRPTd2M5CTlfU",
    "metrics": {
      "sentiment": 100,
      "popularity": 2,
      "convenience": 5
    },
    "locality": "Trivandrum",
    "types": [
      "atm",
      "finance",
      "point_of_interest",
      "establishment"
    ],
    "location": {
      "lat": 8.500233,
      "lng": 76.945251
    }
  },
  {
    "id": "ChIJYQ08Uxy7BTsRbjZzymOo_ls",
    "name": "HDFC Bank ATM",
    "score": 62.5,
    "rating": 5,
    "reviews": 1,
    "price_level": null,
    "address": "No 25/2344, Premier Towers, Mahatma Gandhi Rd, Ayurveda College Junction, Pulimoodu, Thiruvananthapuram, Kerala 695001, India",
    "image": "images/places/AZLasHpUzG3aEZOA.jpg",
    "category": "banking",
    "vibes": [
      "Public Sector",
      "Private"
    ],
    "website": "https://www.hdfc.bank.in/branch-locator/kerala/thiruvananthapuram/hdfcbank-atm-mgroadtrivandrumatm",
    "phone": "094097 67967",
    "map_url": "https://www.google.com/maps/place/?q=place_id:ChIJYQ08Uxy7BTsRbjZzymOo_ls",
    "metrics": {
      "sentiment": 100,
      "popularity": 1,
      "convenience": 5
    },
    "locality": "Trivandrum",
    "types": [
      "atm",
      "finance",
      "point_of_interest",
      "establishment"
    ],
    "location": {
      "lat": 8.49222,
      "lng": 76.94731000000002
    }
  },
  {
    "id": "ChIJ2QcM_my7BTsRX3sQXV5ivXY",
    "name": "Axis Bank ATM",
    "score": 62.5,
    "rating": 5,
    "reviews": 1,
    "price_level": null,
    "address": "TC 30/1398, Amrit plaza Pettah, Pattoor - Vanchiyoor Rd, Vanchiyoor, Thiruvananthapuram, Kerala 695035, India",
    "image": "images/places/AZLasHpKGGyusd5V.jpg",
    "category": "banking",
    "vibes": [
      "Private"
    ],
    "website": "https://branch.axisbank.com/axis-bank-atm-pattoor-atm-vanchiyoor-thiruvananthapuram-90474/Home?utm_source=locator&utm_medium=googleplaces",
    "phone": "1860 500 5555",
    "map_url": "https://www.google.com/maps/place/?q=place_id:ChIJ2QcM_my7BTsRX3sQXV5ivXY",
    "metrics": {
      "sentiment": 100,
      "popularity": 1,
      "convenience": 5
    },
    "locality": "Trivandrum",
    "types": [
      "atm",
      "finance",
      "point_of_interest",
      "establishment"
    ],
    "location": {
      "lat": 8.49728,
      "lng": 76.93800999999999
    }
  },
  {
    "id": "ChIJsyPe6Qa7BTsRXKW4muVeplo",
    "name": "HDFC Bank ATM",
    "score": 62.5,
    "rating": 5,
    "reviews": 1,
    "price_level": null,
    "address": "Gr Flr, RV Tower, Palayam University, Punnen Rd, Vanross, Palayam, Thiruvananthapuram, Kerala 695001, India",
    "image": "images/places/AZLasHpOmEuOB9dU.jpg",
    "category": "banking",
    "vibes": [
      "Private"
    ],
    "website": "https://www.hdfc.bank.in/branch-locator/kerala/thiruvananthapuram/hdfcbank-atm-punnenroadpalayamatm",
    "phone": "094097 67967",
    "map_url": "https://www.google.com/maps/place/?q=place_id:ChIJsyPe6Qa7BTsRXKW4muVeplo",
    "metrics": {
      "sentiment": 100,
      "popularity": 1,
      "convenience": 5
    },
    "locality": "Palayam",
    "types": [
      "atm",
      "finance",
      "point_of_interest",
      "establishment"
    ],
    "location": {
      "lat": 8.5003777,
      "lng": 76.9510256
    }
  },
  {
    "id": "ChIJw8hT09G7BTsRmQWJ2YVDTl0",
    "name": "Thiruvananthapuram District Co-operative bank Nanthancode",
    "score": 59.1,
    "rating": 4.7,
    "reviews": 6,
    "price_level": null,
    "address": "GX84+488, Nanthancodu, Thiruvananthapuram, Kerala 695003, India",
    "image": "images/places/AZLasHpxGolfMJXf.jpg",
    "category": "banking",
    "vibes": [
      "Cooperative"
    ],
    "website": null,
    "phone": "0471 231 6651",
    "map_url": "https://www.google.com/maps/place/?q=place_id:ChIJw8hT09G7BTsRmQWJ2YVDTl0",
    "metrics": {
      "sentiment": 93,
      "popularity": 6,
      "convenience": 5
    },
    "locality": "Trivandrum",
    "types": [
      "bank",
      "finance",
      "point_of_interest",
      "establishment"
    ],
    "location": {
      "lat": 8.515283499999999,
      "lng": 76.9558316
    }
  },
  {
    "id": "ChIJH4twBry7BTsR6bUx2ct9_tQ",
    "name": "Punjab National Bank - ATM",
    "score": 59,
    "rating": 4.7,
    "reviews": 3,
    "price_level": null,
    "address": "No TC 27/2213 Uppalam Road, Junction, opposite General Hospital Road, Statue, Palayam, Kochi, Thiruvananthapuram, Kerala 682024, India",
    "image": null,
    "category": "banking",
    "vibes": [
      "Public Sector",
      "Cooperative"
    ],
    "website": "https://locate.pnbindia.in/punjab-national-bank-atm-public-sector-bank-statue-junction-kochi-499221/Home?utm_source=locator&utm_medium=googleplaces",
    "phone": "1800 1800",
    "map_url": "https://www.google.com/maps/place/?q=place_id:ChIJH4twBry7BTsR6bUx2ct9_tQ",
    "metrics": {
      "sentiment": 93,
      "popularity": 3,
      "convenience": 5
    },
    "locality": "Statue",
    "types": [
      "atm",
      "finance",
      "point_of_interest",
      "establishment"
    ],
    "location": {
      "lat": 8.49809,
      "lng": 76.94669379999999
    }
  },
  {
    "id": "ChIJIcQjVmy7BTsRYKsNc0cf2FQ",
    "name": "Equitas small finance bank - Thiruvananthapuram",
    "score": 54.8,
    "rating": 4.3,
    "reviews": 24,
    "price_level": null,
    "address": "TC No : 15, TN Samrudhi Chambers, 1695(9, DPI, Vazhuthacaud, Thiruvananthapuram, Kerala 695014, India",
    "image": "images/places/AZLasHpoCxyi2fyJ.jpg",
    "category": "banking",
    "vibes": [
      "Cooperative"
    ],
    "website": "https://www.equitasbank.com/",
    "phone": "1800 103 1222",
    "map_url": "https://www.google.com/maps/place/?q=place_id:ChIJIcQjVmy7BTsRYKsNc0cf2FQ",
    "metrics": {
      "sentiment": 83,
      "popularity": 24,
      "convenience": 5
    },
    "locality": "Vazhuthacaud",
    "types": [
      "bank",
      "finance",
      "point_of_interest",
      "establishment"
    ],
    "location": {
      "lat": 8.500392999999999,
      "lng": 76.9586125
    }
  },
  {
    "id": "ChIJ05MBgKO7BTsRZG21h0UMnWw",
    "name": "The Trivandrum Co-Operative Urban Bank Limited",
    "score": 53,
    "rating": 4.2,
    "reviews": 10,
    "price_level": null,
    "address": "FWRW+5Q2, Mahatma Gandhi Rd, Vanchiyoor, Thiruvananthapuram, Kerala 695001, India",
    "image": "images/places/AZLasHqLzsRmhJu2.jpg",
    "category": "banking",
    "vibes": [
      "Cooperative"
    ],
    "website": null,
    "phone": null,
    "map_url": "https://www.google.com/maps/place/?q=place_id:ChIJ05MBgKO7BTsRZG21h0UMnWw",
    "metrics": {
      "sentiment": 80,
      "popularity": 10,
      "convenience": 5
    },
    "locality": "Trivandrum",
    "types": [
      "bank",
      "finance",
      "point_of_interest",
      "establishment"
    ],
    "location": {
      "lat": 8.490395699999999,
      "lng": 76.9467939
    }
  },
  {
    "id": "ChIJiyczPqG7BTsR7DU-3-46-sY",
    "name": "Karnataka Bank - Thiruvananthapuram Branch",
    "score": 52.7,
    "rating": 4.1,
    "reviews": 36,
    "price_level": null,
    "address": "Vijayam Tower, No. 28/1304 (1 & 2, Thakaraparambu Rd, Nalumukku, Pazhavangadi, Thiruvananthapuram, Kerala 695023, India",
    "image": "images/places/AZLasHp-PmKbYXK1.jpg",
    "category": "banking",
    "vibes": [
      "Cooperative"
    ],
    "website": "https://www.karnatakabank.bank.in/",
    "phone": "080 4456 6189",
    "map_url": "https://www.google.com/maps/place/?q=place_id:ChIJiyczPqG7BTsR7DU-3-46-sY",
    "metrics": {
      "sentiment": 78,
      "popularity": 36,
      "convenience": 5
    },
    "locality": "Trivandrum",
    "types": [
      "bank",
      "finance",
      "point_of_interest",
      "establishment"
    ],
    "location": {
      "lat": 8.486552399999999,
      "lng": 76.94406599999999
    }
  },
  {
    "id": "ChIJ1T6K5-i7BTsRdlLrxxmFYIY",
    "name": "CANARA BANK - TRIVANDRUM EDAPAZHANJI",
    "score": 52.1,
    "rating": 4.1,
    "reviews": 18,
    "price_level": null,
    "address": "SY.NO.37/78/12787,OPP ARTECH CENTRIX BUILDING, GX38+HH8, CSM Nagar, Edapazhanji, Thiruvananthapuram, Kerala 695010, India",
    "image": "images/places/AZLasHpdoDkoc38F.jpg",
    "category": "banking",
    "vibes": [
      "Public Sector",
      "Cooperative"
    ],
    "website": null,
    "phone": "1800 1030",
    "map_url": "https://www.google.com/maps/place/?q=place_id:ChIJ1T6K5-i7BTsRdlLrxxmFYIY",
    "metrics": {
      "sentiment": 78,
      "popularity": 18,
      "convenience": 5
    },
    "locality": "Trivandrum",
    "types": [
      "bank",
      "finance",
      "point_of_interest",
      "establishment"
    ],
    "location": {
      "lat": 8.5038175,
      "lng": 76.9665127
    }
  },
  {
    "id": "ChIJK1JdlqW7BTsRxz0vxYi8YYw",
    "name": "State Bank of India ATM",
    "score": 52.1,
    "rating": 4.1,
    "reviews": 16,
    "price_level": null,
    "address": "FXP3+Q5H, Central Theatre Rd, Pazhavangadi, Chalai Bazaar, Chalai, Thiruvananthapuram, Kerala 695001, India",
    "image": "images/places/AZLasHp1t3HAAdAP.jpg",
    "category": "banking",
    "vibes": [],
    "website": null,
    "phone": "1800 11 2211",
    "map_url": "https://www.google.com/maps/place/?q=place_id:ChIJK1JdlqW7BTsRxz0vxYi8YYw",
    "metrics": {
      "sentiment": 78,
      "popularity": 16,
      "convenience": 5
    },
    "locality": "Trivandrum",
    "types": [
      "atm",
      "finance",
      "point_of_interest",
      "establishment"
    ],
    "location": {
      "lat": 8.4869366,
      "lng": 76.9529817
    }
  },
  {
    "id": "ChIJoZsnn6S7BTsR35WKbNpOHhE",
    "name": "SBI ATM",
    "score": 52.1,
    "rating": 4.1,
    "reviews": 15,
    "price_level": null,
    "address": "Pb No 22, Anacutchery, Near, Secretariat, Palayam, Thiruvananthapuram, Kerala 695001, India",
    "image": "images/places/AZLasHr_ac1iohQh.jpg",
    "category": "banking",
    "vibes": [
      "Public Sector",
      "Cooperative"
    ],
    "website": "https://bank.sbi/",
    "phone": "1800 1234",
    "map_url": "https://www.google.com/maps/place/?q=place_id:ChIJoZsnn6S7BTsR35WKbNpOHhE",
    "metrics": {
      "sentiment": 78,
      "popularity": 15,
      "convenience": 5
    },
    "locality": "Palayam",
    "types": [
      "atm",
      "finance",
      "point_of_interest",
      "establishment"
    ],
    "location": {
      "lat": 8.497302,
      "lng": 76.94846199999999
    }
  },
  {
    "id": "ChIJTY_qEMy7BTsRessm6NQlpuE",
    "name": "CANARA BANK - TRIVANDRUM PTP NAGAR",
    "score": 50.8,
    "rating": 4,
    "reviews": 19,
    "price_level": null,
    "address": "NIRMALYAM TC 2616, TIRUMALA S.O, 2617, PTP Nagar, Thirumala, Thiruvananthapuram, Kerala 695038, India",
    "image": "images/places/AZLasHokZ1aX5QK9.jpg",
    "category": "banking",
    "vibes": [
      "Public Sector",
      "Cooperative"
    ],
    "website": null,
    "phone": "1800 1030",
    "map_url": "https://www.google.com/maps/place/?q=place_id:ChIJTY_qEMy7BTsRessm6NQlpuE",
    "metrics": {
      "sentiment": 75,
      "popularity": 19,
      "convenience": 5
    },
    "locality": "Trivandrum",
    "types": [
      "bank",
      "finance",
      "point_of_interest",
      "establishment"
    ],
    "location": {
      "lat": 8.5146281,
      "lng": 76.9891368
    }
  },
  {
    "id": "ChIJ6-6aYLm7BTsRo5ZEWVUlahI",
    "name": "SBI Branch Thiruvananthapuram",
    "score": 50,
    "rating": 3.6,
    "reviews": 130,
    "price_level": null,
    "address": "P.B, FWXX+H98, 14, Mahatma Gandhi Rd, Palayam, Thiruvananthapuram, Kerala 695001, India",
    "image": "images/places/AZLasHpMX6I7rNfx.jpg",
    "category": "banking",
    "vibes": [
      "Public Sector",
      "Cooperative"
    ],
    "website": "https://bank.sbi/",
    "phone": "1800 1234",
    "map_url": "https://www.google.com/maps/place/?q=place_id:ChIJ6-6aYLm7BTsRo5ZEWVUlahI",
    "metrics": {
      "sentiment": 68,
      "popularity": 130,
      "convenience": 5
    },
    "locality": "Palayam",
    "types": [
      "bank",
      "finance",
      "point_of_interest",
      "establishment"
    ],
    "location": {
      "lat": 8.499547,
      "lng": 76.94881099999999
    }
  },
  {
    "id": "ChIJ7yTvFbS7BTsROY6p29igCi8",
    "name": "Union Bank of India ATM",
    "score": 49.4,
    "rating": 3.9,
    "reviews": 7,
    "price_level": null,
    "address": "GX25+4WC, Vazhuthacaud - Poojappura Rd, Cotton Hill, Vazhuthacaud, Thiruvananthapuram, Kerala 695014, India",
    "image": "images/places/AZLasHrjLngRBkNG.jpg",
    "category": "banking",
    "vibes": [
      "Cooperative"
    ],
    "website": null,
    "phone": null,
    "map_url": "https://www.google.com/maps/place/?q=place_id:ChIJ7yTvFbS7BTsROY6p29igCi8",
    "metrics": {
      "sentiment": 73,
      "popularity": 7,
      "convenience": 5
    },
    "locality": "Vazhuthacaud",
    "types": [
      "atm",
      "finance",
      "point_of_interest",
      "establishment"
    ],
    "location": {
      "lat": 8.500306199999999,
      "lng": 76.9597642
    }
  },
  {
    "id": "ChIJ2TunAK67BTsR8SiJ-I3sc6k",
    "name": "SBI ATM",
    "score": 47,
    "rating": 3.7,
    "reviews": 9,
    "price_level": null,
    "address": "FXV5+8CM, Thycaud, Thiruvananthapuram, Kerala 695014, India",
    "image": "images/places/AZLasHomd_zqRVKh.jpg",
    "category": "banking",
    "vibes": [
      "Public Sector",
      "Cooperative"
    ],
    "website": null,
    "phone": "1800 11 2211",
    "map_url": "https://www.google.com/maps/place/?q=place_id:ChIJ2TunAK67BTsR8SiJ-I3sc6k",
    "metrics": {
      "sentiment": 68,
      "popularity": 9,
      "convenience": 5
    },
    "locality": "Trivandrum",
    "types": [
      "atm",
      "finance",
      "point_of_interest",
      "establishment"
    ],
    "location": {
      "lat": 8.4933441,
      "lng": 76.9585376
    }
  },
  {
    "id": "ChIJaYrycX-7BTsR6s9Sd7deAak",
    "name": "CANARA BANK - TRIVANDRUM CHALAI",
    "score": 45.9,
    "rating": 3.6,
    "reviews": 19,
    "price_level": null,
    "address": "I FLOOR,IBRAHIM CO. BLDG, S.O, Chalai Bazaar, Chalai, Thiruvananthapuram, Kerala 695036, India",
    "image": "images/places/AZLasHoz7DyUxj0Y.jpg",
    "category": "banking",
    "vibes": [
      "Public Sector",
      "Cooperative"
    ],
    "website": null,
    "phone": "1800 1030",
    "map_url": "https://www.google.com/maps/place/?q=place_id:ChIJaYrycX-7BTsR6s9Sd7deAak",
    "metrics": {
      "sentiment": 65,
      "popularity": 19,
      "convenience": 5
    },
    "locality": "Trivandrum",
    "types": [
      "bank",
      "finance",
      "point_of_interest",
      "establishment"
    ],
    "location": {
      "lat": 8.4846807,
      "lng": 76.9531035
    }
  },
  {
    "id": "ChIJUaHVIKS7BTsRKQt40ZVAao4",
    "name": "ICICI Bank ATM",
    "score": 45.5,
    "rating": 3.6,
    "reviews": 5,
    "price_level": null,
    "address": "S.L. Enclave, Railway Station Rd, Overbridge, Santhi Nagar, Pulimoodu, Thiruvananthapuram, Kerala 695001, India",
    "image": "images/places/AZLasHq92wRV04Vs.jpg",
    "category": "banking",
    "vibes": [
      "Private"
    ],
    "website": null,
    "phone": null,
    "map_url": "https://www.google.com/maps/place/?q=place_id:ChIJUaHVIKS7BTsRKQt40ZVAao4",
    "metrics": {
      "sentiment": 65,
      "popularity": 5,
      "convenience": 5
    },
    "locality": "Trivandrum",
    "types": [
      "atm",
      "finance",
      "point_of_interest",
      "establishment"
    ],
    "location": {
      "lat": 8.488136899999999,
      "lng": 76.9488203
    }
  },
  {
    "id": "ChIJIcneIwG7BTsRSObBakMgj9A",
    "name": "CANARA BANK - TRIVANDRUM PATTOOR",
    "score": 44.9,
    "rating": 3.5,
    "reviews": 22,
    "price_level": null,
    "address": "TC 27/1674,VANCHIYOOR-PATTOOR ROAD,PATTOOR, S.O, Rishimangalam, Vanchiyoor, Thiruvananthapuram, Kerala 695035, India",
    "image": "images/places/AZLasHpXH8-T8S87.jpg",
    "category": "banking",
    "vibes": [
      "Public Sector",
      "Cooperative"
    ],
    "website": null,
    "phone": "1800 1030",
    "map_url": "https://www.google.com/maps/place/?q=place_id:ChIJIcneIwG7BTsRSObBakMgj9A",
    "metrics": {
      "sentiment": 63,
      "popularity": 22,
      "convenience": 5
    },
    "locality": "Trivandrum",
    "types": [
      "bank",
      "finance",
      "point_of_interest",
      "establishment"
    ],
    "location": {
      "lat": 8.4969836,
      "lng": 76.9383276
    }
  },
  {
    "id": "ChIJW3hSvKW7BTsR-ewnpnKFSbQ",
    "name": "SBI ATM",
    "score": 44.4,
    "rating": 3.5,
    "reviews": 4,
    "price_level": null,
    "address": "Tc/72, 1203(1, Chalai Kudappanakkunnu, Attakulangara, Thiruvananthapuram, Kerala 695004, India",
    "image": "images/places/AZLasHptcLauVFF_.jpg",
    "category": "banking",
    "vibes": [
      "Public Sector",
      "Cooperative"
    ],
    "website": "https://bank.sbi/",
    "phone": "1800 1234",
    "map_url": "https://www.google.com/maps/place/?q=place_id:ChIJW3hSvKW7BTsR-ewnpnKFSbQ",
    "metrics": {
      "sentiment": 63,
      "popularity": 4,
      "convenience": 5
    },
    "locality": "Trivandrum",
    "types": [
      "atm",
      "finance",
      "point_of_interest",
      "establishment"
    ],
    "location": {
      "lat": 8.5250411,
      "lng": 76.9430304
    }
  },
  {
    "id": "ChIJlddXtae7BTsRkoMWnt_4fNI",
    "name": "City Union Bank Trivandrum",
    "score": 44,
    "rating": 3.4,
    "reviews": 28,
    "price_level": null,
    "address": "Old TC 38/553(8), New TC 71/285, Ground Floor, Blue Tower, Power House Rd, Chalai Bazaar, Chalai, Thiruvananthapuram, Kerala 695036, India",
    "image": "images/places/AZLasHpSyzJbXx0m.jpg",
    "category": "banking",
    "vibes": [
      "Cooperative"
    ],
    "website": "http://www.cityunionbank.bank.in/?utm_source=gmb&utm_medium=organic&utm_campaign=tuskmelon-cityunionbank",
    "phone": "0471 246 7303",
    "map_url": "https://www.google.com/maps/place/?q=place_id:ChIJlddXtae7BTsRkoMWnt_4fNI",
    "metrics": {
      "sentiment": 61,
      "popularity": 28,
      "convenience": 5
    },
    "locality": "Trivandrum",
    "types": [
      "bank",
      "finance",
      "point_of_interest",
      "establishment"
    ],
    "location": {
      "lat": 8.4843522,
      "lng": 76.9542367
    }
  },
  {
    "id": "ChIJf8uGEKa7BTsRxNH_cbmDJPM",
    "name": "Union Bank of India ATM",
    "score": 43.1,
    "rating": 3.4,
    "reviews": 5,
    "price_level": null,
    "address": "FXP2+VRC, Kanyakumari - Panvel Rd, Overbridge, Chalai Bazaar, Thampanoor, Thiruvananthapuram, Kerala 695001, India",
    "image": "images/places/AZLasHoMrpGhQwKK.jpg",
    "category": "banking",
    "vibes": [
      "Cooperative"
    ],
    "website": null,
    "phone": null,
    "map_url": "https://www.google.com/maps/place/?q=place_id:ChIJf8uGEKa7BTsRxNH_cbmDJPM",
    "metrics": {
      "sentiment": 60,
      "popularity": 5,
      "convenience": 5
    },
    "locality": "Thampanoor",
    "types": [
      "atm",
      "finance",
      "point_of_interest",
      "establishment"
    ],
    "location": {
      "lat": 8.4871802,
      "lng": 76.9520144
    }
  },
  {
    "id": "ChIJndD8r2K7BTsR_NKq1yKjogk",
    "name": "CANARA BANK - TRIVANDRUM VAZHUTHACAUD",
    "score": 42.8,
    "rating": 3.3,
    "reviews": 34,
    "price_level": null,
    "address": "Panorema, opp. Tagore Theatre, Vazhuthacaud, Thiruvananthapuram, Kerala 695010, India",
    "image": "images/places/AZLasHodES_ncHpi.jpg",
    "category": "banking",
    "vibes": [
      "Public Sector",
      "Cooperative"
    ],
    "website": null,
    "phone": "1800 1030",
    "map_url": "https://www.google.com/maps/place/?q=place_id:ChIJndD8r2K7BTsR_NKq1yKjogk",
    "metrics": {
      "sentiment": 58,
      "popularity": 34,
      "convenience": 5
    },
    "locality": "Vazhuthacaud",
    "types": [
      "bank",
      "finance",
      "point_of_interest",
      "establishment"
    ],
    "location": {
      "lat": 8.504101,
      "lng": 76.96009819999999
    }
  },
  {
    "id": "ChIJY0T1VMe5BTsR9VtlRCDyLUM",
    "name": "CANARA BANK - TRIVANDRUM ULLOOR",
    "score": 42.5,
    "rating": 3.3,
    "reviews": 23,
    "price_level": null,
    "address": "TC 2/4-1 I FLOOR, MEDICAL COLLEGE S.O, Ulloor Junction, Ulloor Garden, Ulloor, Thiruvananthapuram, Kerala 695011, India",
    "image": "images/places/AZLasHqrnBlwhHO9.jpg",
    "category": "banking",
    "vibes": [
      "Public Sector",
      "Cooperative"
    ],
    "website": null,
    "phone": "1800 1030",
    "map_url": "https://www.google.com/maps/place/?q=place_id:ChIJY0T1VMe5BTsR9VtlRCDyLUM",
    "metrics": {
      "sentiment": 58,
      "popularity": 23,
      "convenience": 5
    },
    "locality": "Ulloor",
    "types": [
      "bank",
      "finance",
      "point_of_interest",
      "establishment"
    ],
    "location": {
      "lat": 8.530245599999999,
      "lng": 76.9290497
    }
  },
  {
    "id": "ChIJ3zSbraC7BTsRiWu_kBU6IpA",
    "name": "ATM - Trivandrum Co-operative Bank",
    "score": 41.9,
    "rating": 3.3,
    "reviews": 3,
    "price_level": null,
    "address": "695023, Fort, Padma Nagar, Pazhavangadi, Thiruvananthapuram, Kerala 695023, India",
    "image": "images/places/AZLasHoEN71BArkL.jpg",
    "category": "banking",
    "vibes": [],
    "website": null,
    "phone": null,
    "map_url": "https://www.google.com/maps/place/?q=place_id:ChIJ3zSbraC7BTsRiWu_kBU6IpA",
    "metrics": {
      "sentiment": 58,
      "popularity": 3,
      "convenience": 5
    },
    "locality": "Trivandrum",
    "types": [
      "atm",
      "finance",
      "point_of_interest",
      "establishment"
    ],
    "location": {
      "lat": 8.482833,
      "lng": 76.9466758
    }
  },
  {
    "id": "ChIJldXjHQq7BTsR3H6vmLwezOw",
    "name": "State Bank ATM",
    "score": 41.9,
    "rating": 3.3,
    "reviews": 4,
    "price_level": null,
    "address": "FWJW+JQ4, Mahatma Gandhi Rd, Fort, East Fort, Pazhavangadi, Thiruvananthapuram, Kerala 695023, India",
    "image": "images/places/AZLasHrp1NnUNK0R.jpg",
    "category": "banking",
    "vibes": [],
    "website": null,
    "phone": null,
    "map_url": "https://www.google.com/maps/place/?q=place_id:ChIJldXjHQq7BTsR3H6vmLwezOw",
    "metrics": {
      "sentiment": 58,
      "popularity": 4,
      "convenience": 5
    },
    "locality": "East Fort",
    "types": [
      "atm",
      "finance",
      "point_of_interest",
      "establishment"
    ],
    "location": {
      "lat": 8.4815159,
      "lng": 76.9469551
    }
  },
  {
    "id": "ChIJBZ4AbFe7BTsRIfzDI9LCau4",
    "name": "CANARA BANK - TRIVANDRUM SASTHAMANGALAM",
    "score": 39.5,
    "rating": 3,
    "reviews": 40,
    "price_level": null,
    "address": "TC 9/1093, SASTHAMANGALAM SASTHAMANGALAM S.O, Jawahar Nagar, Sasthamangalam, Thiruvananthapuram, Kerala 695010, India",
    "image": "images/places/AZLasHrzSzuyRQQl.jpg",
    "category": "banking",
    "vibes": [
      "Public Sector",
      "Cooperative"
    ],
    "website": null,
    "phone": "1800 1030",
    "map_url": "https://www.google.com/maps/place/?q=place_id:ChIJBZ4AbFe7BTsRIfzDI9LCau4",
    "metrics": {
      "sentiment": 51,
      "popularity": 40,
      "convenience": 5
    },
    "locality": "Sasthamangalam",
    "types": [
      "bank",
      "finance",
      "point_of_interest",
      "establishment"
    ],
    "location": {
      "lat": 8.5130924,
      "lng": 76.97162209999999
    }
  },
  {
    "id": "ChIJsWfxzty7BTsR3ASJa4N6PiU",
    "name": "HDFC Bank ATM",
    "score": 38.5,
    "rating": 3,
    "reviews": 15,
    "price_level": null,
    "address": "BOB Plaza, near Plamoodu Bridge, Plammoodu, Thiruvananthapuram, Kerala 695003, India",
    "image": "images/places/AZLasHpdlck9LY8l.jpg",
    "category": "banking",
    "vibes": [
      "Private",
      "Cooperative"
    ],
    "website": "https://www.hdfc.bank.in/branch-locator/kerala/thiruvananthapuram/hdfcbank-atm-plammoodu",
    "phone": "094097 67967",
    "map_url": "https://www.google.com/maps/place/?q=place_id:ChIJsWfxzty7BTsR3ASJa4N6PiU",
    "metrics": {
      "sentiment": 50,
      "popularity": 15,
      "convenience": 5
    },
    "locality": "Trivandrum",
    "types": [
      "atm",
      "finance",
      "point_of_interest",
      "establishment"
    ],
    "location": {
      "lat": 8.515154599999999,
      "lng": 76.9455526
    }
  },
  {
    "id": "ChIJqzYUd6S7BTsRoZFVoIe37bQ",
    "name": "Punjab National Bank ATM",
    "score": 37.1,
    "rating": 2.9,
    "reviews": 7,
    "price_level": null,
    "address": "FWQW+WW9, Kanyakumari - Panvel Rd, Overbridge, Santhi Nagar, Pulimoodu, Thiruvananthapuram, Kerala 695001, India",
    "image": "images/places/AZLasHrvAks1pOUh.jpg",
    "category": "banking",
    "vibes": [],
    "website": null,
    "phone": null,
    "map_url": "https://www.google.com/maps/place/?q=place_id:ChIJqzYUd6S7BTsRoZFVoIe37bQ",
    "metrics": {
      "sentiment": 48,
      "popularity": 7,
      "convenience": 5
    },
    "locality": "Trivandrum",
    "types": [
      "atm",
      "finance",
      "point_of_interest",
      "establishment"
    ],
    "location": {
      "lat": 8.489785800000002,
      "lng": 76.9473477
    }
  },
  {
    "id": "ChIJzxFmvq-7BTsRCKiVUqK5dQg",
    "name": "CANARA BANK - TRIVANDRUM PERUNTHANNI",
    "score": 36.7,
    "rating": 2.8,
    "reviews": 30,
    "price_level": null,
    "address": "JUNCTION, ENJAKKAL, TC 36/1025(1-4),AARATTU ROAD, Perunthanni, Vallakkadavu, Thiruvananthapuram, Kerala 695008, India",
    "image": "images/places/AZLasHq7cQ8kWoAX.jpg",
    "category": "banking",
    "vibes": [
      "Public Sector",
      "Cooperative"
    ],
    "website": null,
    "phone": "1800 1030",
    "map_url": "https://www.google.com/maps/place/?q=place_id:ChIJzxFmvq-7BTsRCKiVUqK5dQg",
    "metrics": {
      "sentiment": 46,
      "popularity": 30,
      "convenience": 5
    },
    "locality": "Trivandrum",
    "types": [
      "bank",
      "finance",
      "point_of_interest",
      "establishment"
    ],
    "location": {
      "lat": 8.4803211,
      "lng": 76.93510409999999
    }
  },
  {
    "id": "ChIJN5GkUbu7BTsR7MMeUPz3l9I",
    "name": "ICICI Bank Thiruvananthapuram Trivandrum",
    "score": 36.4,
    "rating": 2.5,
    "reviews": 131,
    "price_level": null,
    "address": "TC 25, ICICI Bank Ltd, 2491, Mahatma Gandhi Rd, Santhi Nagar, Pulimoodu, Thiruvananthapuram, Kerala 695001, India",
    "image": "images/places/AZLasHp-_jkrtgmm.jpg",
    "category": "banking",
    "vibes": [
      "Private",
      "Cooperative"
    ],
    "website": null,
    "phone": "090206 67777",
    "map_url": "https://www.google.com/maps/place/?q=place_id:ChIJN5GkUbu7BTsR7MMeUPz3l9I",
    "metrics": {
      "sentiment": 40,
      "popularity": 131,
      "convenience": 5
    },
    "locality": "Trivandrum",
    "types": [
      "bank",
      "finance",
      "point_of_interest",
      "establishment"
    ],
    "location": {
      "lat": 8.4931986,
      "lng": 76.94775539999999
    }
  },
  {
    "id": "ChIJQZNFH8q5BTsRgCfAaSF0RU4",
    "name": "CANARA BANK - TRIVANDRUM MUTTADA",
    "score": 35.5,
    "rating": 2.7,
    "reviews": 35,
    "price_level": null,
    "address": "SREE PADMAM, TC 3, S.O, 865, Muttada - Paruthippara Rd, Muttada, Thoppil Nagar, Thiruvananthapuram, Kerala 695025, India",
    "image": "images/places/AZLasHrTuczgociO.jpg",
    "category": "banking",
    "vibes": [
      "Public Sector",
      "Cooperative"
    ],
    "website": null,
    "phone": "1800 1030",
    "map_url": "https://www.google.com/maps/place/?q=place_id:ChIJQZNFH8q5BTsRgCfAaSF0RU4",
    "metrics": {
      "sentiment": 43,
      "popularity": 35,
      "convenience": 5
    },
    "locality": "Trivandrum",
    "types": [
      "bank",
      "finance",
      "point_of_interest",
      "establishment"
    ],
    "location": {
      "lat": 8.5346966,
      "lng": 76.94733459999999
    }
  },
  {
    "id": "ChIJW8m9RdS7BTsRSxKxH3iUshY",
    "name": "State Bank ATM and CDM",
    "score": 33.6,
    "rating": 2.6,
    "reviews": 17,
    "price_level": null,
    "address": "GXF6+552, Kowdiar Ave, Kowdiar, Thiruvananthapuram, Kerala 695003, India",
    "image": "images/places/AZLasHr5grrd_K9c.jpg",
    "category": "banking",
    "vibes": [
      "Cooperative"
    ],
    "website": null,
    "phone": null,
    "map_url": "https://www.google.com/maps/place/?q=place_id:ChIJW8m9RdS7BTsRSxKxH3iUshY",
    "metrics": {
      "sentiment": 40,
      "popularity": 17,
      "convenience": 5
    },
    "locality": "Kowdiar",
    "types": [
      "atm",
      "finance",
      "point_of_interest",
      "establishment"
    ],
    "location": {
      "lat": 8.522895799999999,
      "lng": 76.9603946
    }
  },
  {
    "id": "ChIJ77oI8Ty7BTsRn90S7wYEVI0",
    "name": "CANARA BANK - TRIVANDRUM PETTAH",
    "score": 33.5,
    "rating": 2.6,
    "reviews": 14,
    "price_level": null,
    "address": "TC 31/ 586, 587 NEAR KANJIRAVILAKAM TEMPE BEACH ROAD, S.O, PO, Pettah, Thiruvananthapuram, Kerala 695024, India",
    "image": "images/places/AZLasHrrlSbbn8Km.jpg",
    "category": "banking",
    "vibes": [
      "Public Sector",
      "Cooperative"
    ],
    "website": null,
    "phone": "1800 1030",
    "map_url": "https://www.google.com/maps/place/?q=place_id:ChIJ77oI8Ty7BTsRn90S7wYEVI0",
    "metrics": {
      "sentiment": 40,
      "popularity": 14,
      "convenience": 5
    },
    "locality": "Trivandrum",
    "types": [
      "bank",
      "finance",
      "point_of_interest",
      "establishment"
    ],
    "location": {
      "lat": 8.4940719,
      "lng": 76.926947
    }
  },
  {
    "id": "ChIJ24a-kbe7BTsRq7VUyx5dH-A",
    "name": "Bank Of India ATM",
    "score": 32.1,
    "rating": 2.5,
    "reviews": 2,
    "price_level": null,
    "address": "GX33+3F7, Nandavanam, Palayam, Thiruvananthapuram, Kerala 695033, India",
    "image": "images/places/AZLasHrlauGAeQtn.jpg",
    "category": "banking",
    "vibes": [],
    "website": null,
    "phone": null,
    "map_url": "https://www.google.com/maps/place/?q=place_id:ChIJ24a-kbe7BTsRq7VUyx5dH-A",
    "metrics": {
      "sentiment": 38,
      "popularity": 2,
      "convenience": 5
    },
    "locality": "Palayam",
    "types": [
      "atm",
      "finance",
      "point_of_interest",
      "establishment"
    ],
    "location": {
      "lat": 8.5026774,
      "lng": 76.9536533
    }
  },
  {
    "id": "ChIJdVmaEKa7BTsRzQc-Nji6z-Q",
    "name": "Bank Of India ATM",
    "score": 25.9,
    "rating": 2,
    "reviews": 4,
    "price_level": null,
    "address": "FXP2+VR2, Overbridge, Santhi Nagar, Thampanoor, Thiruvananthapuram, Kerala 695001, India",
    "image": "images/places/AZLasHo8EoXdWCu-.jpg",
    "category": "banking",
    "vibes": [],
    "website": null,
    "phone": null,
    "map_url": "https://www.google.com/maps/place/?q=place_id:ChIJdVmaEKa7BTsRzQc-Nji6z-Q",
    "metrics": {
      "sentiment": 25,
      "popularity": 4,
      "convenience": 5
    },
    "locality": "Thampanoor",
    "types": [
      "atm",
      "finance",
      "point_of_interest",
      "establishment"
    ],
    "location": {
      "lat": 8.4871395,
      "lng": 76.9520058
    }
  },
  {
    "id": "ChIJtxqQShG9BTsRvi_7Sf3yGyw",
    "name": "HDFC Bank ATM",
    "score": 13.6,
    "rating": 1,
    "reviews": 2,
    "price_level": null,
    "address": "Door No TC 91/770/2, Gr Flr, Angel Tower, Anayara, Venpalavattom, Thiruvananthapuram, Kerala 695029, India",
    "image": "images/places/AZLasHq5F_NyPONN.jpg",
    "category": "banking",
    "vibes": [
      "Private",
      "Cooperative"
    ],
    "website": "https://www.hdfc.bank.in/branch-locator/kerala/thiruvananthapuram/hdfcbank-atm-venpalavattomatm",
    "phone": "094097 67967",
    "map_url": "https://www.google.com/maps/place/?q=place_id:ChIJtxqQShG9BTsRvi_7Sf3yGyw",
    "metrics": {
      "sentiment": 0,
      "popularity": 2,
      "convenience": 5
    },
    "locality": "Trivandrum",
    "types": [
      "atm",
      "finance",
      "point_of_interest",
      "establishment"
    ],
    "location": {
      "lat": 8.5067846,
      "lng": 76.91106649999999
    }
  }
]